truecolorhsi/__init__.py
truecolorhsi/accessories.py
truecolorhsi/visualization.py
TrueColorHSI-0.1.3.dist-info/LICENSE
TrueColorHSI-0.1.3.dist-info/METADATA
TrueColorHSI-0.1.3.dist-info/WHEEL
TrueColorHSI-0.1.3.dist-info/top_level.txt
TrueColorHSI-0.1.3.dist-info/RECORD
