Metadata-Version: 2.2
Name: TrueColorHSI
Version: 0.1.3
Summary: A package for accurate and vivid visualization of hyperspectral images
Home-page: https://github.com/fz-rit/TrueColorHSI
Author: Fei Zhang
Author-email: fzhcis@rit.edu
Classifier: Programming Language :: Python :: 3
Classifier: License :: OSI Approved :: MIT License
Classifier: Operating System :: OS Independent
Requires-Python: >=3.9
License-File: LICENSE
Requires-Dist: spectral
Requires-Dist: matplotlib
Requires-Dist: scipy
Requires-Dist: scikit-image
Requires-Dist: pysptools
Requires-Dist: colour-science
Requires-Dist: ipykernel
Dynamic: author
Dynamic: author-email
Dynamic: classifier
Dynamic: description
Dynamic: description-content-type
Dynamic: home-page
Dynamic: requires-dist
Dynamic: requires-python
Dynamic: summary
